{
"meta":{"test_sets":[],"test_metrics":[],"learn_metrics":[{"best_value":"Min","name":"MultiClass"}],"launch_mode":"Train","parameters":"","iteration_count":300,"learn_sets":["learn"],"name":"experiment"},
"iterations":[
{"learn":[1.375556788],"iteration":0,"passed_time":0.110956284,"remaining_time":33.17592891},
{"learn":[1.206325307],"iteration":1,"passed_time":0.1684946813,"remaining_time":25.10570751},
{"learn":[1.066647743],"iteration":2,"passed_time":0.2191638918,"remaining_time":21.69722529},
{"learn":[0.9712690768],"iteration":3,"passed_time":0.2693640651,"remaining_time":19.93294082},
{"learn":[0.8913100755],"iteration":4,"passed_time":0.316438762,"remaining_time":18.66988696},
{"learn":[0.8192392433],"iteration":5,"passed_time":0.3734274523,"remaining_time":18.29794516},
{"learn":[0.7508242548],"iteration":6,"passed_time":0.4180163446,"remaining_time":17.49696985},
{"learn":[0.6898643895],"iteration":7,"passed_time":0.4617452839,"remaining_time":16.85370286},
{"learn":[0.6426839872],"iteration":8,"passed_time":0.5013374432,"remaining_time":16.20991066},
{"learn":[0.5929411561],"iteration":9,"passed_time":0.5400724427,"remaining_time":15.66210084},
{"learn":[0.552812823],"iteration":10,"passed_time":0.5873895309,"remaining_time":15.43232495},
{"learn":[0.518425851],"iteration":11,"passed_time":0.6307597974,"remaining_time":15.13823514},
{"learn":[0.4878888998],"iteration":12,"passed_time":0.6723861399,"remaining_time":14.84421709},
{"learn":[0.459524731],"iteration":13,"passed_time":0.713135494,"remaining_time":14.56833938},
{"learn":[0.4329157997],"iteration":14,"passed_time":0.7545854122,"remaining_time":14.33712283},
{"learn":[0.4094679647],"iteration":15,"passed_time":0.8048751114,"remaining_time":14.28653323},
{"learn":[0.3856751536],"iteration":16,"passed_time":0.8543781593,"remaining_time":14.22288348},
{"learn":[0.3722636928],"iteration":17,"passed_time":0.8931940546,"remaining_time":13.99337352},
{"learn":[0.3523927078],"iteration":18,"passed_time":0.9323850231,"remaining_time":13.78948376},
{"learn":[0.3340909039],"iteration":19,"passed_time":0.9732611415,"remaining_time":13.62565598},
{"learn":[0.3191514265],"iteration":20,"passed_time":1.016221166,"remaining_time":13.50122407},
{"learn":[0.3028309724],"iteration":21,"passed_time":1.056057137,"remaining_time":13.344722},
{"learn":[0.2894234255],"iteration":22,"passed_time":1.093849676,"remaining_time":13.17375479},
{"learn":[0.2756727076],"iteration":23,"passed_time":1.133149476,"remaining_time":13.03121898},
{"learn":[0.2637053304],"iteration":24,"passed_time":1.172179234,"remaining_time":12.89397157},
{"learn":[0.25379095],"iteration":25,"passed_time":1.215161533,"remaining_time":12.80593308},
{"learn":[0.2438852473],"iteration":26,"passed_time":1.266922961,"remaining_time":12.80999882},
{"learn":[0.232548644],"iteration":27,"passed_time":1.32510961,"remaining_time":12.87249335},
{"learn":[0.2230476882],"iteration":28,"passed_time":1.371612685,"remaining_time":12.81748406},
{"learn":[0.2138517183],"iteration":29,"passed_time":1.410976135,"remaining_time":12.69878521},
{"learn":[0.2054958374],"iteration":30,"passed_time":1.453478021,"remaining_time":12.61243831},
{"learn":[0.1981161145],"iteration":31,"passed_time":1.496359911,"remaining_time":12.53201425},
{"learn":[0.1911169694],"iteration":32,"passed_time":1.540733555,"remaining_time":12.46593513},
{"learn":[0.1854080699],"iteration":33,"passed_time":1.582475495,"remaining_time":12.38054358},
{"learn":[0.1785622994],"iteration":34,"passed_time":1.627246087,"remaining_time":12.32057751},
{"learn":[0.170379206],"iteration":35,"passed_time":1.665658759,"remaining_time":12.2148309},
{"learn":[0.1635296299],"iteration":36,"passed_time":1.707190012,"remaining_time":12.13489116},
{"learn":[0.1576463117],"iteration":37,"passed_time":1.749147213,"remaining_time":12.05990973},
{"learn":[0.1530454615],"iteration":38,"passed_time":1.7876006,"remaining_time":11.96317324},
{"learn":[0.1484615073],"iteration":39,"passed_time":1.832044057,"remaining_time":11.90828637},
{"learn":[0.1439661035],"iteration":40,"passed_time":1.880836045,"remaining_time":11.88137892},
{"learn":[0.1398544676],"iteration":41,"passed_time":1.923636194,"remaining_time":11.81662233},
{"learn":[0.1350500929],"iteration":42,"passed_time":1.964433686,"remaining_time":11.74091761},
{"learn":[0.1318432422],"iteration":43,"passed_time":2.009577243,"remaining_time":11.69208578},
{"learn":[0.1267222894],"iteration":44,"passed_time":2.050276438,"remaining_time":11.61823315},
{"learn":[0.1227325765],"iteration":45,"passed_time":2.08857472,"remaining_time":11.53256476},
{"learn":[0.1193463727],"iteration":46,"passed_time":2.126637093,"remaining_time":11.44764222},
{"learn":[0.1157029703],"iteration":47,"passed_time":2.166864662,"remaining_time":11.37603948},
{"learn":[0.1125044],"iteration":48,"passed_time":2.20780466,"remaining_time":11.30936673},
{"learn":[0.1099016025],"iteration":49,"passed_time":2.246784714,"remaining_time":11.23392357},
{"learn":[0.1069098302],"iteration":50,"passed_time":2.285655632,"remaining_time":11.1593775},
{"learn":[0.1045187867],"iteration":51,"passed_time":2.328254943,"remaining_time":11.10398511},
{"learn":[0.1018904131],"iteration":52,"passed_time":2.367555315,"remaining_time":11.03370118},
{"learn":[0.09895851344],"iteration":53,"passed_time":2.408248999,"remaining_time":10.97091211},
{"learn":[0.09619515452],"iteration":54,"passed_time":2.451965997,"remaining_time":10.92239399},
{"learn":[0.0943834682],"iteration":55,"passed_time":2.492986614,"remaining_time":10.86229882},
{"learn":[0.09218870434],"iteration":56,"passed_time":2.529930221,"remaining_time":10.78549199},
{"learn":[0.09010364865],"iteration":57,"passed_time":2.5726318,"remaining_time":10.73408441},
{"learn":[0.08830658059],"iteration":58,"passed_time":2.61261148,"remaining_time":10.67185367},
{"learn":[0.08632760916],"iteration":59,"passed_time":2.654368711,"remaining_time":10.61747485},
{"learn":[0.08413729989],"iteration":60,"passed_time":2.700862024,"remaining_time":10.58206596},
{"learn":[0.08230306587],"iteration":61,"passed_time":2.740853632,"remaining_time":10.52134136},
{"learn":[0.08072773455],"iteration":62,"passed_time":2.783690969,"remaining_time":10.47198031},
{"learn":[0.079065293],"iteration":63,"passed_time":2.827563929,"remaining_time":10.42664199},
{"learn":[0.07774028732],"iteration":64,"passed_time":2.865952391,"remaining_time":10.36152018},
{"learn":[0.07625519495],"iteration":65,"passed_time":2.905205809,"remaining_time":10.30027514},
{"learn":[0.07474126606],"iteration":66,"passed_time":2.944093441,"remaining_time":10.2384145},
{"learn":[0.07372579198],"iteration":67,"passed_time":2.984028325,"remaining_time":10.18080252},
{"learn":[0.07233451306],"iteration":68,"passed_time":3.024051792,"remaining_time":10.12399948},
{"learn":[0.07057943642],"iteration":69,"passed_time":3.079877642,"remaining_time":10.11959797},
{"learn":[0.06914445182],"iteration":70,"passed_time":3.128158384,"remaining_time":10.08941225},
{"learn":[0.06803907488],"iteration":71,"passed_time":3.173911265,"remaining_time":10.05071901},
{"learn":[0.06699756948],"iteration":72,"passed_time":3.214538472,"remaining_time":9.995893605},
{"learn":[0.06588907986],"iteration":73,"passed_time":3.254523446,"remaining_time":9.939490523},
{"learn":[0.06496972845],"iteration":74,"passed_time":3.295865427,"remaining_time":9.887596281},
{"learn":[0.06356191651],"iteration":75,"passed_time":3.342640625,"remaining_time":9.851993421},
{"learn":[0.06273475503],"iteration":76,"passed_time":3.390536219,"remaining_time":9.819345154},
{"learn":[0.06147744506],"iteration":77,"passed_time":3.437273578,"remaining_time":9.783009413},
{"learn":[0.06050132342],"iteration":78,"passed_time":3.479595257,"remaining_time":9.734057619},
{"learn":[0.05961574029],"iteration":79,"passed_time":3.517895905,"remaining_time":9.674213738},
{"learn":[0.05877159876],"iteration":80,"passed_time":3.561015927,"remaining_time":9.62793195},
{"learn":[0.05775197807],"iteration":81,"passed_time":3.606914244,"remaining_time":9.589113479},
{"learn":[0.0566673815],"iteration":82,"passed_time":3.659873356,"remaining_time":9.568584558},
{"learn":[0.05602116183],"iteration":83,"passed_time":3.708494289,"remaining_time":9.536128172},
{"learn":[0.05483876234],"iteration":84,"passed_time":3.747252324,"remaining_time":9.478344114},
{"learn":[0.05405850153],"iteration":85,"passed_time":3.784480984,"remaining_time":9.417196868},
{"learn":[0.05308230187],"iteration":86,"passed_time":3.823295731,"remaining_time":9.360482653},
{"learn":[0.05228133075],"iteration":87,"passed_time":3.864601899,"remaining_time":9.310177303},
{"learn":[0.05185388816],"iteration":88,"passed_time":3.910304772,"remaining_time":9.27049783},
{"learn":[0.05142635716],"iteration":89,"passed_time":3.925121393,"remaining_time":9.158616584},
{"learn":[0.05083441939],"iteration":90,"passed_time":3.964820876,"remaining_time":9.106017178},
{"learn":[0.04991293784],"iteration":91,"passed_time":4.010368985,"remaining_time":9.066921184},
{"learn":[0.04924974938],"iteration":92,"passed_time":4.049962312,"remaining_time":9.014432242},
{"learn":[0.04855332356],"iteration":93,"passed_time":4.088404445,"remaining_time":8.959694848},
{"learn":[0.04803592771],"iteration":94,"passed_time":4.128191243,"remaining_time":8.908202156},
{"learn":[0.04759438891],"iteration":95,"passed_time":4.167744836,"remaining_time":8.856457778},
{"learn":[0.04691788173],"iteration":96,"passed_time":4.206021271,"remaining_time":8.802291938},
{"learn":[0.04609840791],"iteration":97,"passed_time":4.24621964,"remaining_time":8.752411912},
{"learn":[0.04537791795],"iteration":98,"passed_time":4.286892795,"remaining_time":8.703691432},
{"learn":[0.04483971005],"iteration":99,"passed_time":4.308187903,"remaining_time":8.616375807},
{"learn":[0.04456164034],"iteration":100,"passed_time":4.333537347,"remaining_time":8.538355762},
{"learn":[0.04405649039],"iteration":101,"passed_time":4.381922705,"remaining_time":8.506085251},
{"learn":[0.04367175768],"iteration":102,"passed_time":4.425503145,"remaining_time":8.464311841},
{"learn":[0.0429989709],"iteration":103,"passed_time":4.468387297,"remaining_time":8.421191445},
{"learn":[0.04240841141],"iteration":104,"passed_time":4.510697118,"remaining_time":8.377008934},
{"learn":[0.04179295115],"iteration":105,"passed_time":4.571191805,"remaining_time":8.366143492},
{"learn":[0.04141936464],"iteration":106,"passed_time":4.612343232,"remaining_time":8.319460222},
{"learn":[0.04090851096],"iteration":107,"passed_time":4.659796232,"remaining_time":8.28408219},
{"learn":[0.04054876454],"iteration":108,"passed_time":4.698513979,"remaining_time":8.233175871},
{"learn":[0.03994971993],"iteration":109,"passed_time":4.741198212,"remaining_time":8.189342367},
{"learn":[0.03935107967],"iteration":110,"passed_time":4.782432556,"remaining_time":8.143060838},
{"learn":[0.03885673202],"iteration":111,"passed_time":4.827351638,"remaining_time":8.103054536},
{"learn":[0.03836903573],"iteration":112,"passed_time":4.866879984,"remaining_time":8.054040328},
{"learn":[0.03789084779],"iteration":113,"passed_time":4.911483189,"remaining_time":8.013472571},
{"learn":[0.0375039744],"iteration":114,"passed_time":4.968817447,"remaining_time":7.993315023},
{"learn":[0.0370952176],"iteration":115,"passed_time":5.012887702,"remaining_time":7.951477044},
{"learn":[0.03670020779],"iteration":116,"passed_time":5.056308267,"remaining_time":7.908584725},
{"learn":[0.03647302617],"iteration":117,"passed_time":5.103801571,"remaining_time":7.871965135},
{"learn":[0.03605355211],"iteration":118,"passed_time":5.141361025,"remaining_time":7.820053324},
{"learn":[0.03566588027],"iteration":119,"passed_time":5.184413097,"remaining_time":7.776619645},
{"learn":[0.03521481724],"iteration":120,"passed_time":5.224376178,"remaining_time":7.728622611},
{"learn":[0.03481723759],"iteration":121,"passed_time":5.263055596,"remaining_time":7.678884394},
{"learn":[0.03448546114],"iteration":122,"passed_time":5.303776396,"remaining_time":7.632263594},
{"learn":[0.03415997191],"iteration":123,"passed_time":5.345396959,"remaining_time":7.587015038},
{"learn":[0.03382138835],"iteration":124,"passed_time":5.387407045,"remaining_time":7.542369863},
{"learn":[0.03346100046],"iteration":125,"passed_time":5.430692954,"remaining_time":7.499528366},
{"learn":[0.03316600697],"iteration":126,"passed_time":5.479387212,"remaining_time":7.464047147},
{"learn":[0.03305362837],"iteration":127,"passed_time":5.505459417,"remaining_time":7.397961091},
{"learn":[0.03275220716],"iteration":128,"passed_time":5.54940042,"remaining_time":7.356181953},
{"learn":[0.03255676552],"iteration":129,"passed_time":5.574937253,"remaining_time":7.290302562},
{"learn":[0.03224007841],"iteration":130,"passed_time":5.616763953,"remaining_time":7.24605426},
{"learn":[0.03200516822],"iteration":131,"passed_time":5.660604858,"remaining_time":7.204406183},
{"learn":[0.0316886972],"iteration":132,"passed_time":5.699789506,"remaining_time":7.156878553},
{"learn":[0.03150140333],"iteration":133,"passed_time":5.706501682,"remaining_time":7.069248353},
{"learn":[0.03114470949],"iteration":134,"passed_time":5.748555861,"remaining_time":7.026012719},
{"learn":[0.03084958751],"iteration":135,"passed_time":5.788613824,"remaining_time":6.980387259},
{"learn":[0.03066843816],"iteration":136,"passed_time":5.829878683,"remaining_time":6.936279017},
{"learn":[0.0304134147],"iteration":137,"passed_time":5.873721691,"remaining_time":6.895238507},
{"learn":[0.03006530423],"iteration":138,"passed_time":5.914517547,"remaining_time":6.850628238},
{"learn":[0.02980788872],"iteration":139,"passed_time":5.956361099,"remaining_time":6.807269827},
{"learn":[0.02952527725],"iteration":140,"passed_time":5.995071013,"remaining_time":6.760399227},
{"learn":[0.02947757067],"iteration":141,"passed_time":5.998076125,"remaining_time":6.673915688},
{"learn":[0.02920127709],"iteration":142,"passed_time":6.039496812,"remaining_time":6.63077622},
{"learn":[0.02893665566],"iteration":143,"passed_time":6.08026236,"remaining_time":6.58695089},
{"learn":[0.0286865093],"iteration":144,"passed_time":6.119779422,"remaining_time":6.541833175},
{"learn":[0.02843411414],"iteration":145,"passed_time":6.160542222,"remaining_time":6.49810618},
{"learn":[0.02838228059],"iteration":146,"passed_time":6.19673909,"remaining_time":6.449667216},
{"learn":[0.02806224881],"iteration":147,"passed_time":6.237350788,"remaining_time":6.405927836},
{"learn":[0.02783052496],"iteration":148,"passed_time":6.281180193,"remaining_time":6.365491336},
{"learn":[0.02747043],"iteration":149,"passed_time":6.320633535,"remaining_time":6.320633535},
{"learn":[0.02724750992],"iteration":150,"passed_time":6.36505906,"remaining_time":6.280753642},
{"learn":[0.0269580767],"iteration":151,"passed_time":6.404639242,"remaining_time":6.236096104},
{"learn":[0.02675872409],"iteration":152,"passed_time":6.442433958,"remaining_time":6.189789489},
{"learn":[0.02656911866],"iteration":153,"passed_time":6.483939069,"remaining_time":6.147111066},
{"learn":[0.02619754997],"iteration":154,"passed_time":6.523408289,"remaining_time":6.102543238},
{"learn":[0.02598611428],"iteration":155,"passed_time":6.56193992,"remaining_time":6.057175311},
{"learn":[0.0258123084],"iteration":156,"passed_time":6.603894735,"remaining_time":6.015012402},
{"learn":[0.02563890987],"iteration":157,"passed_time":6.646402904,"remaining_time":5.973349445},
{"learn":[0.02542724521],"iteration":158,"passed_time":6.698410561,"remaining_time":5.940099931},
{"learn":[0.02523668149],"iteration":159,"passed_time":6.749082305,"remaining_time":5.905447017},
{"learn":[0.02501221993],"iteration":160,"passed_time":6.79208929,"remaining_time":5.86397771},
{"learn":[0.02478788031],"iteration":161,"passed_time":6.833428702,"remaining_time":5.821068895},
{"learn":[0.02455034787],"iteration":162,"passed_time":6.879323061,"remaining_time":5.782007726},
{"learn":[0.02436789364],"iteration":163,"passed_time":6.918608264,"remaining_time":5.737382463},
{"learn":[0.02413047079],"iteration":164,"passed_time":6.956052562,"remaining_time":5.691315732},
{"learn":[0.02391637563],"iteration":165,"passed_time":6.997390344,"remaining_time":5.64849582},
{"learn":[0.02373156099],"iteration":166,"passed_time":7.035114179,"remaining_time":5.602815484},
{"learn":[0.02357458732],"iteration":167,"passed_time":7.078503048,"remaining_time":5.561680966},
{"learn":[0.02340565352],"iteration":168,"passed_time":7.115262277,"remaining_time":5.515380819},
{"learn":[0.02328748213],"iteration":169,"passed_time":7.154066501,"remaining_time":5.470756736},
{"learn":[0.02318986258],"iteration":170,"passed_time":7.177305252,"remaining_time":5.414458348},
{"learn":[0.02309932922],"iteration":171,"passed_time":7.220595493,"remaining_time":5.373466413},
{"learn":[0.02295132035],"iteration":172,"passed_time":7.258885026,"remaining_time":5.328776869},
{"learn":[0.02281542416],"iteration":173,"passed_time":7.268144444,"remaining_time":5.26313908},
{"learn":[0.02263112993],"iteration":174,"passed_time":7.317824856,"remaining_time":5.227017755},
{"learn":[0.0224790696],"iteration":175,"passed_time":7.360123254,"remaining_time":5.185541384},
{"learn":[0.02235116986],"iteration":176,"passed_time":7.400986509,"remaining_time":5.143058422},
{"learn":[0.02221345066],"iteration":177,"passed_time":7.44452306,"remaining_time":5.102425918},
{"learn":[0.02206074991],"iteration":178,"passed_time":7.490854176,"remaining_time":5.063650029},
{"learn":[0.02189559409],"iteration":179,"passed_time":7.536079426,"remaining_time":5.024052951},
{"learn":[0.0217509477],"iteration":180,"passed_time":7.579805275,"remaining_time":4.983407888},
{"learn":[0.02160856832],"iteration":181,"passed_time":7.625257349,"remaining_time":4.943848171},
{"learn":[0.02150146788],"iteration":182,"passed_time":7.666575272,"remaining_time":4.901580912},
{"learn":[0.02134703609],"iteration":183,"passed_time":7.689264182,"remaining_time":4.847579593},
{"learn":[0.02119544317],"iteration":184,"passed_time":7.728973214,"remaining_time":4.804496863},
{"learn":[0.02108890454],"iteration":185,"passed_time":7.76742733,"remaining_time":4.760681267},
{"learn":[0.02090953695],"iteration":186,"passed_time":7.808231742,"remaining_time":4.718343245},
{"learn":[0.02077527383],"iteration":187,"passed_time":7.848459525,"remaining_time":4.675678015},
{"learn":[0.0206093994],"iteration":188,"passed_time":7.891105712,"remaining_time":4.63445891},
{"learn":[0.02044905486],"iteration":189,"passed_time":7.934105793,"remaining_time":4.59342967},
{"learn":[0.02033955724],"iteration":190,"passed_time":7.975617947,"remaining_time":4.551530661},
{"learn":[0.020224353],"iteration":191,"passed_time":8.017841209,"remaining_time":4.51003568},
{"learn":[0.02006268467],"iteration":192,"passed_time":8.058660635,"remaining_time":4.46775486},
{"learn":[0.01993098853],"iteration":193,"passed_time":8.094145218,"remaining_time":4.422574191},
{"learn":[0.01979022335],"iteration":194,"passed_time":8.136108185,"remaining_time":4.38098133},
{"learn":[0.01964427484],"iteration":195,"passed_time":8.178008421,"remaining_time":4.339351407},
{"learn":[0.01949741875],"iteration":196,"passed_time":8.216336857,"remaining_time":4.29585125},
{"learn":[0.01937916347],"iteration":197,"passed_time":8.254017997,"remaining_time":4.252069877},
{"learn":[0.01926832477],"iteration":198,"passed_time":8.291874225,"remaining_time":4.208438677},
{"learn":[0.01917208236],"iteration":199,"passed_time":8.33287195,"remaining_time":4.166435975},
{"learn":[0.01905330029],"iteration":200,"passed_time":8.372889712,"remaining_time":4.123960604},
{"learn":[0.01892285612],"iteration":201,"passed_time":8.413202209,"remaining_time":4.081652557},
{"learn":[0.01883996108],"iteration":202,"passed_time":8.454531723,"remaining_time":4.039850134},
{"learn":[0.0187709826],"iteration":203,"passed_time":8.494656679,"remaining_time":3.997485496},
{"learn":[0.01867316208],"iteration":204,"passed_time":8.535169158,"remaining_time":3.955322293},
{"learn":[0.01858895001],"iteration":205,"passed_time":8.578926307,"remaining_time":3.914655694},
{"learn":[0.01850210626],"iteration":206,"passed_time":8.619658495,"remaining_time":3.872600193},
{"learn":[0.01836148075],"iteration":207,"passed_time":8.658924862,"remaining_time":3.829909074},
{"learn":[0.01826785899],"iteration":208,"passed_time":8.699918872,"remaining_time":3.788002954},
{"learn":[0.01817828593],"iteration":209,"passed_time":8.742551141,"remaining_time":3.746807632},
{"learn":[0.01804737917],"iteration":210,"passed_time":8.782294706,"remaining_time":3.704380232},
{"learn":[0.01798113167],"iteration":211,"passed_time":8.82258178,"remaining_time":3.662203758},
{"learn":[0.01788604726],"iteration":212,"passed_time":8.844996497,"remaining_time":3.612745048},
{"learn":[0.01780976257],"iteration":213,"passed_time":8.891465603,"remaining_time":3.573205803},
{"learn":[0.01764953804],"iteration":214,"passed_time":8.935508574,"remaining_time":3.532642925},
{"learn":[0.01755288325],"iteration":215,"passed_time":8.976168898,"remaining_time":3.490732349},
{"learn":[0.01744047951],"iteration":216,"passed_time":9.014851853,"remaining_time":3.448076976},
{"learn":[0.01736802594],"iteration":217,"passed_time":9.037269111,"remaining_time":3.399339757},
{"learn":[0.01725551312],"iteration":218,"passed_time":9.080471009,"remaining_time":3.358530373},
{"learn":[0.01712980221],"iteration":219,"passed_time":9.121444105,"remaining_time":3.316888766},
{"learn":[0.01702407924],"iteration":220,"passed_time":9.159366508,"remaining_time":3.274162688},
{"learn":[0.01690685701],"iteration":221,"passed_time":9.198993339,"remaining_time":3.232078741},
{"learn":[0.01684705928],"iteration":222,"passed_time":9.209929003,"remaining_time":3.180110014},
{"learn":[0.01671303774],"iteration":223,"passed_time":9.2542155,"remaining_time":3.139823116},
{"learn":[0.01663326387],"iteration":224,"passed_time":9.293698933,"remaining_time":3.097899644},
{"learn":[0.01653990303],"iteration":225,"passed_time":9.333268217,"remaining_time":3.056025876},
{"learn":[0.01646761401],"iteration":226,"passed_time":9.357804846,"remaining_time":3.009338122},
{"learn":[0.01637252234],"iteration":227,"passed_time":9.400727732,"remaining_time":2.968650863},
{"learn":[0.01626839742],"iteration":228,"passed_time":9.443224012,"remaining_time":2.927811812},
{"learn":[0.01618043042],"iteration":229,"passed_time":9.484417838,"remaining_time":2.886561951},
{"learn":[0.01610656728],"iteration":230,"passed_time":9.525077607,"remaining_time":2.845153052},
{"learn":[0.01599060449],"iteration":231,"passed_time":9.565403304,"remaining_time":2.803652693},
{"learn":[0.01587572522],"iteration":232,"passed_time":9.591436598,"remaining_time":2.758052584},
{"learn":[0.01579689255],"iteration":233,"passed_time":9.641097193,"remaining_time":2.719283824},
{"learn":[0.0157042719],"iteration":234,"passed_time":9.669191596,"remaining_time":2.67445725},
{"learn":[0.01563529509],"iteration":235,"passed_time":9.699402709,"remaining_time":2.630346497},
{"learn":[0.0155822757],"iteration":236,"passed_time":9.711780312,"remaining_time":2.581612488},
{"learn":[0.01549904241],"iteration":237,"passed_time":9.757428265,"remaining_time":2.541851061},
{"learn":[0.01542623007],"iteration":238,"passed_time":9.795539824,"remaining_time":2.500116859},
{"learn":[0.01536507584],"iteration":239,"passed_time":9.83245581,"remaining_time":2.458113952},
{"learn":[0.015288979],"iteration":240,"passed_time":9.877085083,"remaining_time":2.418041576},
{"learn":[0.01521954098],"iteration":241,"passed_time":9.91903066,"remaining_time":2.37728834},
{"learn":[0.01517183571],"iteration":242,"passed_time":9.931104581,"remaining_time":2.329518358},
{"learn":[0.01509653645],"iteration":243,"passed_time":9.974757647,"remaining_time":2.28928864},
{"learn":[0.0150340006],"iteration":244,"passed_time":10.01755364,"remaining_time":2.248838572},
{"learn":[0.01496624485],"iteration":245,"passed_time":10.05908814,"remaining_time":2.208092518},
{"learn":[0.0148925622],"iteration":246,"passed_time":10.10041133,"remaining_time":2.167294738},
{"learn":[0.01482167499],"iteration":247,"passed_time":10.13827692,"remaining_time":2.12576774},
{"learn":[0.01474248239],"iteration":248,"passed_time":10.17849703,"remaining_time":2.084752404},
{"learn":[0.01467546431],"iteration":249,"passed_time":10.22130141,"remaining_time":2.044260283},
{"learn":[0.01463740137],"iteration":250,"passed_time":10.2576619,"remaining_time":2.002491765},
{"learn":[0.01456920382],"iteration":251,"passed_time":10.3002396,"remaining_time":1.961950401},
{"learn":[0.0145047101],"iteration":252,"passed_time":10.33839112,"remaining_time":1.920570682},
{"learn":[0.01445608978],"iteration":253,"passed_time":10.37897497,"remaining_time":1.879656885},
{"learn":[0.01439357329],"iteration":254,"passed_time":10.42174614,"remaining_time":1.839131671},
{"learn":[0.01434122957],"iteration":255,"passed_time":10.46142363,"remaining_time":1.798057186},
{"learn":[0.0142505049],"iteration":256,"passed_time":10.50451454,"remaining_time":1.757564689},
{"learn":[0.01419055693],"iteration":257,"passed_time":10.5466661,"remaining_time":1.716899132},
{"learn":[0.01413352343],"iteration":258,"passed_time":10.58810256,"remaining_time":1.676108899},
{"learn":[0.01406238162],"iteration":259,"passed_time":10.62775733,"remaining_time":1.63503959},
{"learn":[0.01400109206],"iteration":260,"passed_time":10.668742,"remaining_time":1.594179839},
{"learn":[0.01393866712],"iteration":261,"passed_time":10.71216008,"remaining_time":1.553672072},
{"learn":[0.0138597202],"iteration":262,"passed_time":10.75456482,"remaining_time":1.512999613},
{"learn":[0.01379695745],"iteration":263,"passed_time":10.79551576,"remaining_time":1.472115785},
{"learn":[0.01373605428],"iteration":264,"passed_time":10.83475115,"remaining_time":1.431004869},
{"learn":[0.01365991467],"iteration":265,"passed_time":10.87444821,"remaining_time":1.389967065},
{"learn":[0.01360234796],"iteration":266,"passed_time":10.89321619,"remaining_time":1.346352562},
{"learn":[0.01354240705],"iteration":267,"passed_time":10.93354063,"remaining_time":1.305497389},
{"learn":[0.013524129],"iteration":268,"passed_time":10.94411006,"remaining_time":1.261217145},
{"learn":[0.01348344044],"iteration":269,"passed_time":10.98746465,"remaining_time":1.220829405},
{"learn":[0.01341243953],"iteration":270,"passed_time":11.02832995,"remaining_time":1.18015339},
{"learn":[0.01335914833],"iteration":271,"passed_time":11.07322252,"remaining_time":1.139890554},
{"learn":[0.01329425293],"iteration":272,"passed_time":11.11529365,"remaining_time":1.099314757},
{"learn":[0.01322709724],"iteration":273,"passed_time":11.16117839,"remaining_time":1.059089921},
{"learn":[0.01317499385],"iteration":274,"passed_time":11.20652708,"remaining_time":1.018775189},
{"learn":[0.01313378098],"iteration":275,"passed_time":11.24984741,"remaining_time":0.9782476008},
{"learn":[0.01307730558],"iteration":276,"passed_time":11.29419661,"remaining_time":0.9377852783},
{"learn":[0.01305606246],"iteration":277,"passed_time":11.31420228,"remaining_time":0.8953685254},
{"learn":[0.01298271743],"iteration":278,"passed_time":11.35629864,"remaining_time":0.8547751665},
{"learn":[0.01293076922],"iteration":279,"passed_time":11.39696487,"remaining_time":0.8140689195},
{"learn":[0.01287612623],"iteration":280,"passed_time":11.4372117,"remaining_time":0.7733345993},
{"learn":[0.012824348],"iteration":281,"passed_time":11.47838432,"remaining_time":0.7326628289},
{"learn":[0.01278558272],"iteration":282,"passed_time":11.52247006,"remaining_time":0.6921625123},
{"learn":[0.01273573978],"iteration":283,"passed_time":11.56780063,"remaining_time":0.6517070775},
{"learn":[0.01269503339],"iteration":284,"passed_time":11.60846671,"remaining_time":0.6109719319},
{"learn":[0.01261189113],"iteration":285,"passed_time":11.65189115,"remaining_time":0.5703722941},
{"learn":[0.01254209715],"iteration":286,"passed_time":11.71258658,"remaining_time":0.5305352807},
{"learn":[0.01248874298],"iteration":287,"passed_time":11.77810977,"remaining_time":0.4907545737},
{"learn":[0.01242761126],"iteration":288,"passed_time":11.82795113,"remaining_time":0.4501988318},
{"learn":[0.01237768442],"iteration":289,"passed_time":11.8696289,"remaining_time":0.4092975482},
{"learn":[0.01230894406],"iteration":290,"passed_time":11.91364988,"remaining_time":0.3684633983},
{"learn":[0.01225529007],"iteration":291,"passed_time":11.96034228,"remaining_time":0.3276806103},
{"learn":[0.01220585645],"iteration":292,"passed_time":12.00665839,"remaining_time":0.286848494},
{"learn":[0.01215912089],"iteration":293,"passed_time":12.05354276,"remaining_time":0.2459906687},
{"learn":[0.01211578577],"iteration":294,"passed_time":12.09714313,"remaining_time":0.2050363243},
{"learn":[0.0120736609],"iteration":295,"passed_time":12.13543848,"remaining_time":0.1639924119},
{"learn":[0.01202198797],"iteration":296,"passed_time":12.17891568,"remaining_time":0.1230193503},
{"learn":[0.01197118563],"iteration":297,"passed_time":12.22991188,"remaining_time":0.08207994553},
{"learn":[0.01191513636],"iteration":298,"passed_time":12.27702469,"remaining_time":0.04106028323},
{"learn":[0.01188498173],"iteration":299,"passed_time":12.32215254,"remaining_time":0}
]}